LICENSE
MANIFEST.in
README.rst
setup.py
authorities/__init__.py
authorities/admin.py
authorities/apps.py
authorities/forms.py
authorities/models.py
authorities/tests.py
authorities/urls.py
authorities/views.py
authorities/locale/el/LC_MESSAGES/django.mo
authorities/locale/el/LC_MESSAGES/django.po
authorities/migrations/0001_initial.py
authorities/migrations/0002_auto_20200224_1357.py
authorities/migrations/0003_authority_email.py
authorities/migrations/0004_alter_authority_name_alter_authority_unique_together.py
authorities/migrations/__init__.py
authorities/templates/authorities/authority_detail.html
authorities/templates/authorities/authority_form.html
authorities/templates/authorities/authority_list.html
authorities/templatetags/__init__.py
authorities/templatetags/authorities_tags.py
django_authorities.egg-info/PKG-INFO
django_authorities.egg-info/SOURCES.txt
django_authorities.egg-info/dependency_links.txt
django_authorities.egg-info/not-zip-safe
django_authorities.egg-info/requires.txt
django_authorities.egg-info/top_level.txt